04_shift_register/mux.v
module mux
(
	output	reg 		o_data,
	input				i_data_a,
	input				i_data_b,
	input				i_sel,
	input				i_clk,
	input				i_rstn
);

wire o_ff;

	assign o_ff = (i_sel) ? i_data_b : i_data_a;
	always @(posedge i_clk) begin
		if(!i_rstn) begin
			o_data	= 0;
		end else begin
			o_data <= o_ff;
		end
	end
	
endmodule

04_shift_register/shift_register.v
`include "mux.v"
module shift_register
#(
	parameter NBIT	=	8
)(
	output						o_s,
	output		[NBIT-1 : 0]	o_q,
	input		[NBIT-1 : 0]	i_d,
	input						i_s,
	input						i_sel,
	input						i_clk,
	input						i_rstn
);

mux u_mux_0
(
	.o_data   	(	o_q[0]	),
	.i_data_a 	(	i_s		),
	.i_data_b 	(	i_d[0]	),
	.i_sel    	(	i_sel	),
	.i_clk    	(	i_clk	),
	.i_rstn   	(	i_rstn	)
);

mux u_mux_1
(
	.o_data   	(	o_q[1]	),
	.i_data_a 	(	o_q[0]	),
	.i_data_b 	(	i_d[1]	),
	.i_sel    	(	i_sel	),
	.i_clk    	(	i_clk	),
	.i_rstn   	(	i_rstn	)
);

mux u_mux_2
(
	.o_data   	(	o_q[2]	),
	.i_data_a 	(	o_q[1]	),
	.i_data_b 	(	i_d[2]	),
	.i_sel    	(	i_sel	),
	.i_clk    	(	i_clk	),
	.i_rstn   	(	i_rstn	)
);

mux u_mux_3
(
	.o_data   	(	o_q[3]	),
	.i_data_a 	(	o_q[2]	),
	.i_data_b 	(	i_d[3]	),
	.i_sel    	(	i_sel	),
	.i_clk    	(	i_clk	),
	.i_rstn   	(	i_rstn	)
);

mux u_mux_4
(
	.o_data   	(	o_q[4]	),
	.i_data_a 	(	o_q[3]	),
	.i_data_b 	(	i_d[4]	),
	.i_sel    	(	i_sel	),
	.i_clk    	(	i_clk	),
	.i_rstn   	(	i_rstn	)
);

mux u_mux_5
(
	.o_data   	(	o_q[5]	),
	.i_data_a 	(	o_q[4]	),
	.i_data_b 	(	i_d[5]	),
	.i_sel    	(	i_sel	),
	.i_clk    	(	i_clk	),
	.i_rstn   	(	i_rstn	)
);

mux u_mux_6
(
	.o_data   	(	o_q[6]	),
	.i_data_a 	(	o_q[5]	),
	.i_data_b 	(	i_d[6]	),
	.i_sel    	(	i_sel	),
	.i_clk    	(	i_clk	),
	.i_rstn   	(	i_rstn	)
);

mux u_mux_7
(
	.o_data   	(	o_q[7]	),
	.i_data_a 	(	o_q[6]	),
	.i_data_b 	(	i_d[7]	),
	.i_sel    	(	i_sel	),
	.i_clk    	(	i_clk	),
	.i_rstn   	(	i_rstn	)
);

assign o_s = o_q[7];

endmodule

04_shift_register/shift_register_tb.v
//-------------------------------
//Define & Include
//-------------------------------
`define NBIT		8
`define	SIMCYCLE	20
`define	CLKFREQ		100
`include "shift_register.v"

module shift_register_tb;

//-------------------------------
//Signal Declarations: wire
//-------------------------------

	wire						o_s;
	wire		[`NBIT-1 : 0]	o_q;
//-------------------------------
//Signal Declarations: reg 
//-------------------------------

	reg		[`NBIT-1 : 0]	i_d;
	reg						i_s;
	reg						i_sel;
	reg						i_clk;
	reg						i_rstn;
//-------------------------------
//CLK Generate
//-------------------------------
always #(500/`CLKFREQ) i_clk = ~i_clk;

//-------------------------------
//Module Instance
//-------------------------------

shift_register u_shift_register
(
	.o_s   (	o_s   	) ,
	.o_q   (	o_q   	) ,
	.i_d   (	i_d   	) ,
	.i_s   (	i_s   	) ,
	.i_sel (	i_sel 	) ,
	.i_clk (	i_clk 	) ,
	.i_rstn(	i_rstn	)
);

//-------------------------------
//Tasks
//-------------------------------
task init;
	begin
		i_d	= 0;
		i_s	= 0;
		i_sel = 0;
        i_clk 		= 0;
        i_rstn		= 1;
			
		@(posedge i_clk);
		i_rstn	= 0;

		repeat(20) begin
			@(posedge i_clk);
		end
		
        i_rstn	= 1;

	end
endtask

//-------------------------------
//Test Start
//-------------------------------
integer i;
integer j;
	initial begin
		init();
		for(i=0;i<`SIMCYCLE;i++) begin
			i_d = $urandom;
			i_s = $urandom;
			i_sel = 0;
			@(posedge i_clk);
		end
			i_d = $urandom;
			i_s = $urandom;
			i_sel = 1;
			@(posedge i_clk);
		
		for(i=0;i<`SIMCYCLE;i++) begin
			i_d = $urandom;
			i_s = $urandom;
			i_sel = 0;
			@(posedge i_clk);
		end
		#100;
		$finish;
	end
//-------------------------------
//Dump VCD
//-------------------------------
reg [8*32-1:0]	vcd_file;
	initial begin
		if ($value$plusargs("vcd_file=%s", vcd_file)) begin
			$dumpfile(vcd_file);
			$dumpvars;
		end else begin
			$dumpfile("shift_register_tb.vcd");
			$dumpvars;
		end
	end
endmodule

04_shift_register/vcd/shift_register.vcd
$date
	Mon Jul  8 08:54:13 2024
$end
$version
	Icarus Verilog
$end
$timescale
	1ps
$end
$scope module shift_register_tb $end
$var wire 1 ! o_s $end
$var wire 8 " o_q [7:0] $end
$var reg 1 # i_clk $end
$var reg 8 $ i_d [7:0] $end
$var reg 1 % i_rstn $end
$var reg 1 & i_s $end
$var reg 1 ' i_sel $end
$var reg 256 ( vcd_file [255:0] $end
$var integer 32 ) i [31:0] $end
$scope module u_shift_register $end
$var wire 1 # i_clk $end
$var wire 8 * i_d [7:0] $end
$var wire 1 % i_rstn $end
$var wire 1 & i_s $end
$var wire 1 ' i_sel $end
$var wire 1 ! o_s $end
$var wire 8 + o_q [7:0] $end
$scope module u_mux_0 $end
$var wire 1 # i_clk $end
$var wire 1 & i_data_a $end
$var wire 1 , i_data_b $end
$var wire 1 % i_rstn $end
$var wire 1 ' i_sel $end
$var wire 1 - o_ff $end
$var reg 1 . o_data $end
$upscope $end
$scope module u_mux_1 $end
$var wire 1 # i_clk $end
$var wire 1 / i_data_a $end
$var wire 1 0 i_data_b $end
$var wire 1 % i_rstn $end
$var wire 1 ' i_sel $end
$var wire 1 1 o_ff $end
$var reg 1 2 o_data $end
$upscope $end
$scope module u_mux_2 $end
$var wire 1 # i_clk $end
$var wire 1 3 i_data_a $end
$var wire 1 4 i_data_b $end
$var wire 1 % i_rstn $end
$var wire 1 ' i_sel $end
$var wire 1 5 o_ff $end
$var reg 1 6 o_data $end
$upscope $end
$scope module u_mux_3 $end
$var wire 1 # i_clk $end
$var wire 1 7 i_data_a $end
$var wire 1 8 i_data_b $end
$var wire 1 % i_rstn $end
$var wire 1 ' i_sel $end
$var wire 1 9 o_ff $end
$var reg 1 : o_data $end
$upscope $end
$scope module u_mux_4 $end
$var wire 1 # i_clk $end
$var wire 1 ; i_data_a $end
$var wire 1 < i_data_b $end
$var wire 1 % i_rstn $end
$var wire 1 ' i_sel $end
$var wire 1 = o_ff $end
$var reg 1 > o_data $end
$upscope $end
$scope module u_mux_5 $end
$var wire 1 # i_clk $end
$var wire 1 ? i_data_a $end
$var wire 1 @ i_data_b $end
$var wire 1 % i_rstn $end
$var wire 1 ' i_sel $end
$var wire 1 A o_ff $end
$var reg 1 B o_data $end
$upscope $end
$scope module u_mux_6 $end
$var wire 1 # i_clk $end
$var wire 1 C i_data_a $end
$var wire 1 D i_data_b $end
$var wire 1 % i_rstn $end
$var wire 1 ' i_sel $end
$var wire 1 E o_ff $end
$var reg 1 F o_data $end
$upscope $end
$scope module u_mux_7 $end
$var wire 1 # i_clk $end
$var wire 1 G i_data_a $end
$var wire 1 H i_data_b $end
$var wire 1 % i_rstn $end
$var wire 1 ' i_sel $end
$var wire 1 I o_ff $end
$var reg 1 J o_data $end
$upscope $end
$upscope $end
$scope task init $end
$upscope $end
$upscope $end
$enddefinitions $end
#0
$dumpvars
xJ
xI
0H
xG
xF
xE
0D
xC
xB
xA
0@
x?
x>
x=
0<
x;
x:
x9
08
x7
x6
x5
04
x3
x2
x1
00
x/
x.
0-
0,
bx +
b0 *
bx )
b1011100010111101110110011000110110010000101111011100110110100001101001011001100111010001011111011100100110010101100111011010010111001101110100011001010111001000101110011101100110001101100100 (
0'
0&
1%
b0 $
0#
bx "
x!
$end
#5000
01
05
09
0=
0A
0E
0I
0/
03
07
0;
0?
0C
0G
0!
0.
02
06
0:
0>
0B
0F
b0 "
b0 +
0J
0%
1#
#10000
0#
#15000
1#
#20000
0#
#25000
1#
#30000
0#
#35000
1#
#40000
0#
#45000
1#
#50000
0#
#55000
1#
#60000
0#
#65000
1#
#70000
0#
#75000
1#
#80000
0#
#85000
1#
#90000
0#
#95000
1#
#100000
0#
#105000
1#
#110000
0#
#115000
1#
#120000
0#
#125000
1#
#130000
0#
#135000
1#
#140000
0#
#145000
1#
#150000
0#
#155000
1#
#160000
0#
#165000
1#
#170000
0#
#175000
1#
#180000
0#
#185000
1#
#190000
0#
#195000
1#
#200000
0#
#205000
1-
14
1@
1&
b100100 $
b100100 *
b0 )
1%
1#
#210000
0#
#215000
11
1/
b1 "
b1 +
1.
1,
04
18
0@
b1001 $
b1001 *
b1 )
1#
#220000
0#
#225000
15
13
b11 "
b11 +
12
14
b1101 $
b1101 *
b10 )
1#
#230000
0#
#235000
19
17
b111 "
b111 +
16
0-
08
1@
1D
0&
b1100101 $
b1100101 *
b11 )
1#
#240000
0#
#245000
01
1=
0/
1;
0.
b1110 "
b1110 +
1:
1-
04
0@
0D
1&
b1 $
b1 *
b100 )
1#
#250000
0#
#255000
1A
05
11
1?
03
1/
1>
02
b11101 "
b11101 +
1.
0,
10
14
1<
1@
1D
b1110110 $
b1110110 *
b101 )
1#
#260000
0#
#265000
15
09
1E
13
07
1C
12
06
b111011 "
b111011 +
1B
0-
1,
00
18
0<
1H
0&
b11101101 $
b11101101 *
b110 )
1#
#270000
0#
#275000
1I
0=
19
01
1G
0;
17
0/
1F
0:
16
b1110110 "
b1110110 +
0.
04
1<
b11111001 $
b11111001 *
b111 )
1#
#280000
0#
#285000
05
1=
0A
03
1;
0?
1!
02
1:
0>
b11101100 "
b11101100 +
1J
14
08
0<
0@
b11000101 $
b11000101 *
b1000 )
1#
#290000
0#
#295000
0E
1A
09
0C
1?
07
0B
1>
b11011000 "
b11011000 +
06
1-
1@
1&
b11100101 $
b11100101 *
b1001 )
1#
#300000
0#
#305000
11
0=
1E
0I
1/
0;
1C
0G
1.
0:
1B
b10110001 "
b10110001 +
0F
0,
10
04
1<
0@
0D
0H
b10010 $
b10010 *
b1010 )
1#
#310000
0#
#315000
1I
0A
15
0!
1G
0?
13
0J
1F
0>
b1100011 "
b1100011 +
12
0-
1@
1D
1H
0&
b11110010 $
b11110010 *
b1011 )
1#
#320000
0#
#325000
01
19
0E
0/
17
0C
1!
0.
16
0B
b11000110 "
b11000110 +
1J
1-
00
18
0<
1&
b11101000 $
b11101000 *
b1100 )
1#
#330000
0#
#335000
0I
1=
05
11
0G
1;
03
1/
0F
1:
02
b10001101 "
b10001101 +
1.
14
1<
0@
0H
b1011100 $
b1011100 *
b1101 )
1#
#340000
0#
#345000
15
09
1A
13
07
1?
0!
12
06
1>
b11011 "
b11011 +
0J
1,
0<
1@
0D
b101101 $
b101101 *
b1110 )
1#
#350000
0#
#355000
1E
0=
19
1C
0;
17
1B
0:
b110111 "
b110111 +
16
0-
10
04
08
1D
0&
b1100011 $
b1100011 *
b1111 )
1#
#360000
0#
#365000
01
1=
0A
1I
0/
1;
0?
1G
0.
1:
0>
b1101110 "
b1101110 +
1F
0,
00
0@
0D
1H
b10000000 $
b10000000 *
b10000 )
1#
#370000
0#
#375000
0E
1A
05
1!
0C
1?
03
1J
0B
1>
b11011100 "
b11011100 +
02
1-
10
18
1@
1&
b10101010 $
b10101010 *
b10001 )
1#
#380000
0#
#385000
11
09
1E
0I
1/
07
1C
0G
1.
06
1B
b10111001 "
b10111001 +
0F
14
08
1<
0@
b10010110 $
b10010110 *
b10010 )
1#
#390000
0#
#395000
1I
0=
15
0!
1G
0;
13
0J
1F
0:
b1110011 "
b1110011 +
12
1,
00
18
0<
0H
b1101 $
b1101 *
b10011 )
1#
#400000
0#
#405000
17
0?
1!
16
0>
b11100111 "
b11100111 +
1J
05
19
0I
10
04
1@
1D
1'
b1101011 $
b1101011 *
b10100 )
1#
#410000
0#
#415000
1=
09
0!
1;
07
0J
1:
b1101011 "
b1101011 +
06
0-
15
0A
1I
0,
08
0@
0D
0'
0&
b10 $
b10 *
b0 )
1#
#420000
0#
#425000
01
19
0=
1A
0E
0/
17
0;
1?
0C
1!
0.
16
0:
1>
0B
b11010110 "
b11010110 +
1J
1-
1,
00
14
18
1<
1&
b11101 $
b11101 *
b1 )
1#
#430000
0#
#435000
0I
1E
0A
1=
05
11
0G
1C
0?
1;
03
1/
0F
1B
0>
1:
02
b10101101 "
b10101101 +
1.
0-
10
04
08
0<
1@
0&
b100011 $
b100011 *
b10 )
1#
#440000
0#
#445000
01
15
09
1A
0E
1I
0/
13
07
1?
0C
1G
0!
0.
12
06
1>
0B
1F
b1011010 "
b1011010 +
0J
0,
18
0@
1D
1H
b11001010 $
b11001010 *
b11 )
1#
#450000
0#
#455000
0I
1E
0=
19
05
1!
0G
1C
0;
17
03
1J
0F
1B
0:
16
b10110100 "
b10110100 +
02
08
1<
1@
b11110010 $
b11110010 *
b100 )
1#
#460000
0#
#465000
09
1=
0A
1I
07
1;
0?
1G
0!
06
1:
0>
1F
b1101000 "
b1101000 +
0J
1,
00
0<
0@
0H
b1000001 $
b1000001 *
b101 )
1#
#470000
0#
#475000
0E
1A
0=
1!
0C
1?
0;
1J
0B
1>
b11010000 "
b11010000 +
0:
1-
0,
18
1<
1@
1&
b1111000 $
b1111000 *
b110 )
1#
#480000
0#
#485000
11
0A
1E
0I
1/
0?
1C
0G
1.
0>
1B
b10100001 "
b10100001 +
0F
0-
1,
10
0<
1H
0&
b11101011 $
b11101011 *
b111 )
1#
#490000
0#
#495000
1I
0E
15
01
0!
1G
0C
13
0/
0J
1F
0B
12
b1000010 "
b1000010 +
0.
0,
14
08
0@
b11000110 $
b11000110 *
b1000 )
1#
#500000
0#
#505000
05
19
0I
03
17
0G
1!
02
16
0F
b10000100 "
b10000100 +
1J
00
18
1<
1@
0D
b10111100 $
b10111100 *
b1001 )
1#
#510000
0#
#515000
1=
09
0!
1;
07
0J
1:
b1000 "
b1000 +
06
1-
1,
10
04
0<
0@
0H
1&
b1011 $
b1011 *
b1010 )
1#
#520000
0#
#525000
11
0=
1A
1/
0;
1?
1.
0:
b10001 "
b10001 +
1>
00
14
08
1H
b10000101 $
b10000101 *
b1011 )
1#
#530000
0#
#535000
1E
0A
15
1C
0?
13
1B
0>
b100011 "
b100011 +
12
0-
10
04
18
1<
1@
0H
0&
b111011 $
b111011 *
b1100 )
1#
#540000
0#
#545000
01
19
0E
1I
0/
17
0C
1G
0.
16
0B
b1000110 "
b1000110 +
1F
1-
0,
14
1D
1&
b1111110 $
b1111110 *
b1101 )
1#
#550000
0#
#555000
0I
1=
05
11
1!
0G
1;
03
1/
1J
0F
1:
02
b10001101 "
b10001101 +
1.
1,
00
04
08
1H
b11110001 $
b11110001 *
b1110 )
1#
#560000
0#
#565000
15
09
1A
13
07
1?
0!
12
06
1>
b11011 "
b11011 +
0J
0-
0,
10
0<
0H
0&
b1100010 $
b1100010 *
b1111 )
1#
#570000
0#
#575000
1E
0=
19
01
1C
0;
17
0/
1B
0:
16
b110110 "
b110110 +
0.
1-
1,
14
18
1<
0@
0D
1H
1&
b10011111 $
b10011111 *
b10000 )
1#
#580000
0#
#585000
11
05
1=
0A
1I
1/
03
1;
0?
1G
1.
02
1:
0>
b1101101 "
b1101101 +
1F
0,
00
04
1@
1D
b11111000 $
b11111000 *
b10001 )
1#
#590000
0#
#595000
0E
1A
09
15
1!
0C
1?
07
13
1J
0B
1>
06
b11011011 "
b11011011 +
12
0-
1,
10
14
0@
0D
0&
b10011111 $
b10011111 *
b10010 )
1#
#600000
0#
#605000
01
19
0=
1E
0I
0/
17
0;
1C
0G
0.
16
0:
1B
b10110110 "
b10110110 +
0F
1-
04
1D
0H
1&
b1011011 $
b1011011 *
b10011 )
1#
#610000
0#
#615000
1I
0A
1=
05
11
0!
1G
0?
1;
03
1/
0J
1F
0>
1:
02
b1101101 "
b1101101 +
1.
b10100 )
1#
#620000
0#
#625000
15
09
1A
0E
13
07
1?
0C
1!
12
06
1>
0B
b11011011 "
b11011011 +
1J
1#
#630000
0#
#635000
0I
1E
0=
19
0G
1C
0;
17
0F
1B
0:
b10110111 "
b10110111 +
16
1#
#640000
0#
#645000
1=
0A
1I
1;
0?
1G
0!
1:
0>
1F
b1101111 "
b1101111 +
0J
1#
#650000
0#
#655000
0E
1A
1!
0C
1?
1J
0B
b11011111 "
b11011111 +
1>
1#
#660000
0#
#665000
1E
0I
1C
0G
1B
b10111111 "
b10111111 +
0F
1#
#670000
0#
#675000
1I
0!
1G
0J
b1111111 "
b1111111 +
1F
1#
#680000
0#
#685000
1!
b11111111 "
b11111111 +
1J
1#
