03_adder_cla/fa_4bit.v
module fa_4bit
(
	output		 [3:0]	o_s,
	output				o_c,
	input		[3:0]	i_a,
	input		[3:0]	i_b,
	input				i_c
);

wire [3:0]	p;
wire [3:0]	g;
wire [3:0]	c;
wire [3:0]	ff_p;
wire [3:0]	ff_g;

assign p[0] = i_a[0] ^ i_b[0];
assign p[1] = i_a[1] ^ i_b[1];
assign p[2] = i_a[2] ^ i_b[2];
assign p[3] = i_a[3] ^ i_b[3];

assign g[0] = i_a[0] & i_b[0];
assign g[1] = i_a[1] & i_b[1];
assign g[2] = i_a[2] & i_b[2];
assign g[3] = i_a[3] & i_b[3];

assign ff_g = g[3] | (p[3] & (g[2] | (p[2] & (g[1] | (p[1] & g[0])))));
assign ff_p = p[3] & p[2] & p[1] & p[0];
assign o_c = g | (p & i_c);

assign o_s = i_a + i_b + i_c;
endmodule

03_adder_cla/adder_cla.v
`include "fa_4bit.v"
module adder_cla
#(
	parameter NBIT	=	32
)(
	output		[NBIT-1:0]	o_s,
	output					o_c,
	input		[NBIT-1:0]	i_a,
	input		[NBIT-1:0]	i_b,
	input					i_c
);

wire o_c_0;
wire o_c_1;
wire o_c_2;
wire o_c_3;
wire o_c_4;
wire o_c_5;
wire o_c_6;

fa_4bit u_fa_4bit_0
(
	.o_s	(	o_s[3:0]),
	.o_c	(	o_c_0	),
	.i_a	(	i_a[3:0]),
	.i_b	(	i_b[3:0]),
	.i_c	(	i_c		)
);

fa_4bit u_fa_4bit_1
(
	.o_s	(	o_s[7:4]),
	.o_c	(	o_c_1	),
	.i_a	(	i_a[7:4]	),
	.i_b	(	i_b[7:4]	),
	.i_c	(	o_c_0		)
);

fa_4bit u_fa_4bit_2
(
	.o_s	(	o_s[11:8]),
	.o_c	(	o_c_2	),
	.i_a	(	i_a[11:8]		),
	.i_b	(	i_b[11:8]		),
	.i_c	(	o_c_1		)
);

fa_4bit u_fa_4bit_3 (
	.o_s	(	o_s[15:12]),
	.o_c	(	o_c_3	),
	.i_a	(	i_a[15:12]),
	.i_b	(	i_b[15:12]),
	.i_c	(	o_c_2	)
);

fa_4bit u_fa_4bit_4 (
	.o_s	(	o_s[19:16]),
	.o_c	(	o_c_4	),
	.i_a	(	i_a[19:16]),
	.i_b	(	i_b[19:16]),
	.i_c	(	o_c_3	)
);

fa_4bit u_fa_4bit_5 (
	.o_s	(	o_s[23:20]),
	.o_c	(	o_c_5	),
	.i_a	(	i_a[23:20]),
	.i_b	(	i_b[23:20]),
	.i_c	(	o_c_4	)
);

fa_4bit u_fa_4bit_6 (
	.o_s	(	o_s[27:24]),
	.o_c	(	o_c_6	),
	.i_a	(	i_a[27:24]),
	.i_b	(	i_b[27:24]),
	.i_c	(	o_c_5	)
);

fa_4bit u_fa_4bit_7 (
	.o_s	(	o_s[31:28]),
	.o_c	(	o_c	),
	.i_a	(	i_a[31:28]),
	.i_b	(	i_b[31:28]),
	.i_c	(	o_c_6	)
);

endmodule

03_adder_cla/adder_cla_tb.v
//-------------------------------
//Define & Include
//-------------------------------
`define NBIT		32
`define	SIMCYCLE	20
`define	CLKFREQ		100
`include "adder_cla.v"

module adder_cla_tb;

//-------------------------------
//Signal Declarations: wire
//-------------------------------

	wire		[`NBIT-1:0]	o_s ;
	wire					o_c ;
//-------------------------------
//Signal Declarations: reg 
//-------------------------------
	reg		[`NBIT-1:0]	i_a;
	reg		[`NBIT-1:0]	i_b;
	reg					i_c;
	reg					i_clk;

//-------------------------------
//CLK Generate
//-------------------------------
always #(500/`CLKFREQ) i_clk = ~i_clk;

//-------------------------------
//Module Instance
//-------------------------------

adder_cla u_adder_cla
(
	.o_s	(	o_s	),
	.o_c	(	o_c	),
	.i_a	(	i_a	),
	.i_b	(	i_b	),
	.i_c	(	i_c	)
);

//-------------------------------
//Tasks
//-------------------------------
task init;
	begin
		i_a	= 0;
		i_b	= 0;
		i_c = 0;
        i_clk 		= 0;

		repeat(10) 	
		@(posedge i_clk);
	end
endtask

//-------------------------------
//Test Start
//-------------------------------
integer i;
	initial begin
		init();
		for(i=0;i<`SIMCYCLE;i++) begin
			i_a = $urandom;
			i_b = $urandom;
			i_c = $urandom;
			@(posedge i_clk);
		end
		#100;
		$finish;
	end

//-------------------------------
//Dump VCD
//-------------------------------
reg [8*32-1:0]	vcd_file;
	initial begin
		if ($value$plusargs("vcd_file=%s", vcd_file)) begin
			$dumpfile(vcd_file);
			$dumpvars;
		end else begin
			$dumpfile("adder_cla_tb.vcd");
			$dumpvars;
		end
	end
endmodule

03_adder_cla/vcd/adder_cla.vcd
$date
	Tue Jul  9 11:16:32 2024
$end
$version
	Icarus Verilog
$end
$timescale
	1ps
$end
$scope module adder_cla_tb $end
$var wire 32 ! o_s [31:0] $end
$var wire 1 " o_c $end
$var reg 32 # i_a [31:0] $end
$var reg 32 $ i_b [31:0] $end
$var reg 1 % i_c $end
$var reg 1 & i_clk $end
$var reg 256 ' vcd_file [255:0] $end
$var integer 32 ( i [31:0] $end
$scope module u_adder_cla $end
$var wire 32 ) i_a [31:0] $end
$var wire 32 * i_b [31:0] $end
$var wire 1 % i_c $end
$var wire 32 + o_s [31:0] $end
$var wire 1 , o_c_6 $end
$var wire 1 - o_c_5 $end
$var wire 1 . o_c_4 $end
$var wire 1 / o_c_3 $end
$var wire 1 0 o_c_2 $end
$var wire 1 1 o_c_1 $end
$var wire 1 2 o_c_0 $end
$var wire 1 " o_c $end
$scope module u_fa_4bit_0 $end
$var wire 4 3 ff_g [3:0] $end
$var wire 4 4 ff_p [3:0] $end
$var wire 4 5 i_a [3:0] $end
$var wire 4 6 i_b [3:0] $end
$var wire 1 % i_c $end
$var wire 4 7 p [3:0] $end
$var wire 4 8 o_s [3:0] $end
$var wire 1 2 o_c $end
$var wire 4 9 g [3:0] $end
$upscope $end
$scope module u_fa_4bit_1 $end
$var wire 4 : ff_g [3:0] $end
$var wire 4 ; ff_p [3:0] $end
$var wire 4 < i_a [3:0] $end
$var wire 4 = i_b [3:0] $end
$var wire 1 2 i_c $end
$var wire 4 > p [3:0] $end
$var wire 4 ? o_s [3:0] $end
$var wire 1 1 o_c $end
$var wire 4 @ g [3:0] $end
$upscope $end
$scope module u_fa_4bit_2 $end
$var wire 4 A ff_g [3:0] $end
$var wire 4 B ff_p [3:0] $end
$var wire 4 C i_a [3:0] $end
$var wire 4 D i_b [3:0] $end
$var wire 1 1 i_c $end
$var wire 4 E p [3:0] $end
$var wire 4 F o_s [3:0] $end
$var wire 1 0 o_c $end
$var wire 4 G g [3:0] $end
$upscope $end
$scope module u_fa_4bit_3 $end
$var wire 4 H ff_g [3:0] $end
$var wire 4 I ff_p [3:0] $end
$var wire 4 J i_a [3:0] $end
$var wire 4 K i_b [3:0] $end
$var wire 1 0 i_c $end
$var wire 4 L p [3:0] $end
$var wire 4 M o_s [3:0] $end
$var wire 1 / o_c $end
$var wire 4 N g [3:0] $end
$upscope $end
$scope module u_fa_4bit_4 $end
$var wire 4 O ff_g [3:0] $end
$var wire 4 P ff_p [3:0] $end
$var wire 4 Q i_a [3:0] $end
$var wire 4 R i_b [3:0] $end
$var wire 1 / i_c $end
$var wire 4 S p [3:0] $end
$var wire 4 T o_s [3:0] $end
$var wire 1 . o_c $end
$var wire 4 U g [3:0] $end
$upscope $end
$scope module u_fa_4bit_5 $end
$var wire 4 V ff_g [3:0] $end
$var wire 4 W ff_p [3:0] $end
$var wire 4 X i_a [3:0] $end
$var wire 4 Y i_b [3:0] $end
$var wire 1 . i_c $end
$var wire 4 Z p [3:0] $end
$var wire 4 [ o_s [3:0] $end
$var wire 1 - o_c $end
$var wire 4 \ g [3:0] $end
$upscope $end
$scope module u_fa_4bit_6 $end
$var wire 4 ] ff_g [3:0] $end
$var wire 4 ^ ff_p [3:0] $end
$var wire 4 _ i_a [3:0] $end
$var wire 4 ` i_b [3:0] $end
$var wire 1 - i_c $end
$var wire 4 a p [3:0] $end
$var wire 4 b o_s [3:0] $end
$var wire 1 , o_c $end
$var wire 4 c g [3:0] $end
$upscope $end
$scope module u_fa_4bit_7 $end
$var wire 4 d ff_g [3:0] $end
$var wire 4 e ff_p [3:0] $end
$var wire 4 f i_a [3:0] $end
$var wire 4 g i_b [3:0] $end
$var wire 1 , i_c $end
$var wire 4 h p [3:0] $end
$var wire 4 i o_s [3:0] $end
$var wire 1 " o_c $end
$var wire 4 j g [3:0] $end
$upscope $end
$upscope $end
$scope task init $end
$upscope $end
$upscope $end
$enddefinitions $end
#0
$dumpvars
b0 j
b0 i
b0 h
b0 g
b0 f
b0 e
b0 d
b0 c
b0 b
b0 a
b0 `
b0 _
b0 ^
b0 ]
b0 \
b0 [
b0 Z
b0 Y
b0 X
b0 W
b0 V
b0 U
b0 T
b0 S
b0 R
b0 Q
b0 P
b0 O
b0 N
b0 M
b0 L
b0 K
b0 J
b0 I
b0 H
b0 G
b0 F
b0 E
b0 D
b0 C
b0 B
b0 A
b0 @
b0 ?
b0 >
b0 =
b0 <
b0 ;
b0 :
b0 9
b0 8
b0 7
b0 6
b0 5
b0 4
b0 3
02
01
00
0/
0.
0-
0,
b0 +
b0 *
b0 )
bx (
b101110001011110111011001100011011001000010111101100001011001000110010001100101011100100101111101100011011011000110000100101110011101100110001101100100 '
0&
0%
b0 $
b0 #
0"
b0 !
$end
#5000
1&
#10000
0&
#15000
1&
#20000
0&
#25000
1&
#30000
0&
#35000
1&
#40000
0&
#45000
1&
#50000
0&
#55000
1&
#60000
0&
#65000
1&
#70000
0&
#75000
1&
#80000
0&
#85000
1&
#90000
0&
#95000
1-
b1 A
12
1/
1.
b101 7
b1010 >
b1011 E
b100 G
b110 L
b1 N
b1100 S
b1 U
b1001 Z
b10 a
b1101 h
b1 6
b1000 =
b1110 D
b101 K
b1001 R
b1000 Y
b100 g
b100 5
b1011 ?
b10 <
b11 F
b101 C
b1000 M
b11 J
b1111 T
b101 Q
b1010 [
b1 X
b11 b
b10 _
b1101 i
b1001 f
b11010011101011111000001110110110 !
b11010011101011111000001110110110 +
b110 8
1%
b1000000100010010101111010000001 $
b1000000100010010101111010000001 *
b10010010000101010011010100100100 #
b10010010000101010011010100100100 )
b0 (
1&
#100000
0&
#105000
b1 3
1"
b1 A
1,
b0 e
1.
b1 V
b1110 7
b1 9
b110 >
b1101 E
b10 G
b10 L
b101 N
b1001 S
b0 U
b100 Z
b1011 \
b111 a
b1011 h
b1101 6
b0 =
b1011 D
b111 K
b1011 Y
b110 `
b1000 g
b1 8
b11 5
b111 ?
b110 <
b1 F
b110 C
b1100 M
b101 J
b1010 T
b0 Q
b1011 [
b1111 X
b1000 b
b1 _
b11001000101110101100000101110001 !
b11001000101110101100000101110001 +
b1100 i
b11 f
b10000110101110010111101100001101 $
b10000110101110010111101100001101 *
b110001111100000101011001100011 #
b110001111100000101011001100011 )
b1 (
1&
#110000
0&
#115000
0"
b0 H
0.
0,
b1 W
b0 3
11
b0 A
b0 4
12
b0 V
0/
0-
b111 7
b0 9
b111 >
b101 S
b1011 a
b11 h
b110 E
b0 G
b1101 L
b0 N
b10 U
b1111 Z
b0 \
b10 6
b1000 ?
b1 =
b10 D
b101 K
b111 R
b11 Y
b1001 `
b11 i
b0 g
b1000 8
b101 5
b111 F
b100 C
b1101 M
b1000 J
b1001 T
b10 Q
b1111 [
b1100 X
b111011111110011101011110001000 !
b111011111110011101011110001000 +
b1011 b
b10 _
b1001001101110101001000010010 $
b1001001101110101001000010010 *
b110010110000101000010001100101 #
b110010110000101000010001100101 )
b10 (
1&
#120000
0&
#125000
1"
1,
b1 ]
1/
1-
b1 3
b1 H
10
1.
b1 d
b100 9
b10 c
b1011 7
b1100 E
b1 G
b11 L
b1100 N
b100 S
b11 U
b1101 a
b1000 j
b110 6
b111 =
b1 D
b1111 K
b11 R
b10 Y
b1011 `
b1011 g
b100 8
b1101 5
b1000 ?
b0 <
b1111 F
b1101 C
b1100 M
b1100 J
b1011 T
b111 Q
b0 [
b1101 X
b10 b
b110 _
b1000010000010111100111110000100 !
b1000010000010111100111110000100 +
b100 i
b1000 f
b10111011001000111111000101110110 $
b10111011001000111111000101110110 *
b10000110110101111100110100001101 #
b10000110110101111100110100001101 )
b11 (
1&
#130000
0&
#135000
0"
1-
01
b1 O
b0 ]
0,
b1 :
b1 H
b0 [
1.
b1 7
b1100 9
b110 >
b0 a
b110 c
b1000 @
b0 E
b111 G
b1010 L
b101 N
b1001 S
b100 U
b1100 j
b1010 8
b1100 6
b1000 =
b111 D
b1101 R
b1101 b
b110 `
b1100 g
b111 ?
b1110 <
b1110 F
b111 C
b101 M
b101 J
b10 T
b100 Q
b10111101000000100101111001111010 !
b10111101000000100101111001111010 +
b1011 i
b1111 f
b11000110001011011111011110001100 $
b11000110001011011111011110001100 *
b11110110110101000101011111101101 #
b11110110110101000101011111101101 )
b100 (
1&
#140000
0&
#145000
b1 V
b0 H
b0 O
1,
b0 W
b0 3
00
0/
b0 d
02
b1100 @
b11 7
b100 9
b0 >
b100 G
b0 N
b0 S
b111 U
b1100 Z
b11 \
b1 a
b10 c
b0 h
b110 j
b101 6
b1100 =
b100 D
b1000 K
b111 R
b1111 Y
b10 `
b110 g
b110 5
b1000 ?
b1100 <
b1000 F
b100 C
b1010 M
b10 J
b1110 T
b111 Q
b11 [
b11 X
b110 b
b11 _
b1101 i
b110 f
b11010110001111101010100010001011 !
b11010110001111101010100010001011 +
b1011 8
0%
b1100010111101111000010011000101 $
b1100010111101111000010011000101 *
b1100011001101110010010011000110 #
b1100011001101110010010011000110 )
b101 (
1&
#150000
0&
#155000
10
11
1,
b1 H
b1 O
b1 d
b1 :
1.
12
1/
1-
1"
b1001 >
b1000 L
b10 U
b1001 a
b10 7
b101 9
b110 @
b101 E
b10 G
b111 N
b1101 S
b111 Z
b1000 \
b1100 h
b11 j
b111 6
b111 =
b10 D
b111 K
b10 R
b1101 Y
b1011 `
b11 g
b1100 8
b101 5
b110 ?
b1110 <
b1010 F
b111 C
b111 M
b1111 J
b10 T
b1111 Q
b1000 [
b1010 X
b1110 b
b10 _
b111110100000100111101001101100 !
b111110100000100111101001101100 +
b11 i
b1111 f
b111011110100100111001001110111 $
b111011110100100111001001110111 *
b11110010101011111111011111100101 #
b11110010101011111111011111100101 )
b110 (
1&
#160000
0&
#165000
0-
b0 O
01
b1 ]
b1 3
0.
b1 V
02
b1 A
1/
b0 e
1"
b1101 Z
b10 \
b1101 7
b10 9
b111 >
b1000 @
b10 E
b1001 G
b1011 L
b100 N
b1100 S
b0 U
b1110 a
b1 c
b11 h
b1100 j
b10 6
b1111 =
b1001 D
b110 K
b0 R
b11 Y
b1001 `
b1111 g
b1 8
b1111 5
b111 ?
b1000 <
b100 F
b1011 C
b100 M
b1101 J
b1101 T
b1100 Q
b1 [
b1110 X
b0 b
b111 _
b11000000000111010100010001110001 !
b11000000000111010100010001110001 +
b1100 i
b1100 f
b11111001001100000110100111110010 $
b11111001001100000110100111110010 *
b11000111111011001101101110001111 #
b11000111111011001101101110001111 )
b111 (
1&
#170000
0&
#175000
b0 3
b0 V
0/
0"
b0 ]
b0 H
00
0,
b0 d
b100 E
b1100 Z
b110 a
b0 9
b10 >
b1100 @
b1010 G
b11 L
b1010 S
b0 \
b0 c
b1 h
b110 j
b101 6
b1100 =
b1110 D
b100 K
b1010 R
b1100 Y
b10 `
b110 g
b1101 8
b1000 5
b1010 ?
b1110 <
b1000 F
b1010 C
b1011 M
b111 J
b1010 T
b0 Q
b1100 [
b0 X
b110 b
b100 _
b11010110110010101011100010101101 !
b11010110110010101011100010101101 +
b1101 i
b111 f
b1100010110010100100111011000101 $
b1100010110010100100111011000101 *
b1110100000000000111101011101000 #
b1110100000000000111101011101000 )
b1000 (
1&
#180000
0&
#185000
b1 ]
11
b1 3
b0 :
b1 O
b1 V
1"
12
b0 E
b100 h
b0 7
b1101 9
b1001 >
b10 @
b1000 G
b111 L
b0 N
b101 S
b1010 U
b10 Z
b1000 \
b1000 a
b110 c
b1 j
b1101 6
b10 =
b1000 D
b101 K
b1011 R
b1010 Y
b110 `
b1 g
b1101 5
b1110 ?
b1011 <
b1 F
b1000 C
b111 M
b10 J
b1001 T
b1110 Q
b10 [
b1000 X
b100 b
b1110 _
b110 i
b101 f
b1100100001010010111000111101011 !
b1100100001010010111000111101011 +
b1011 8
1%
b10110101010110101100000101101 $
b10110101010110101100000101101 *
b1011110100011100010100010111101 #
b1011110100011100010100010111101 )
b1001 (
1&
#190000
0&
#195000
1-
00
b0 ]
01
b1 O
b1 V
1"
b0 3
02
b0 A
1.
1,
b0 @
b101 E
b1110 L
b0 j
b1001 7
b10 9
b110 >
b10 G
b1100 S
b11 U
b1001 Z
b110 \
b100 a
b1 c
b1011 h
b1010 6
b0 =
b111 D
b1000 K
b11 R
b111 Y
b101 `
b1000 g
b11 5
b110 ?
b110 <
b1001 F
b10 C
b1110 M
b110 J
b10 T
b1111 Q
b110 [
b1110 X
b111 b
b1 _
b1100 i
b11 f
b11000111011000101110100101101101 !
b11000111011000101110100101101101 +
b1101 8
0%
b10000101011100111000011100001010 $
b10000101011100111000011100001010 *
b110001111011110110001001100011 #
b110001111011110110001001100011 )
b1010 (
1&
#200000
0&
#205000
b0 O
0-
b0 V
10
0.
0,
b1 d
02
b10 @
b110 L
b1010 7
b0 9
b1000 >
b100 E
b1 G
b0 U
b1 Z
b101 a
b0 c
b100 h
b1001 j
b1010 =
b101 D
b100 K
b1000 R
b1101 g
b0 5
b1100 ?
b10 <
b110 F
b1 C
b111 M
b10 J
b1100 T
b100 Q
b1101 [
b110 X
b101 b
b0 _
b110 i
b1001 f
b1100101110111000111011011001011 !
b1100101110111000111011011001011 +
b1011 8
1%
b11010101011110000100010110101010 $
b11010101011110000100010110101010 *
b10010000011001000010000100100000 #
b10010000011001000010000100100000 )
b1011 (
1&
#210000
0&
#215000
1.
12
11
b1 A
00
1/
b1 ]
1,
b0 d
0"
b1000 L
b1010 Z
b101 7
b10 9
b1 @
b110 E
b1000 G
b11 N
b11 S
b0 \
b10 a
b1001 c
b0 j
b11 6
b1 =
b1000 D
b1011 K
b11 R
b1000 Y
b1001 `
b0 g
b1010 8
b110 5
b1011 ?
b1001 <
b111 F
b1110 C
b1110 M
b11 J
b100 T
b0 Q
b1011 [
b10 X
b100 b
b1011 _
b1010100101101001110011110111010 !
b1010100101101001110011110111010 +
b101 i
b100 f
b1001100000111011100000010011 $
b1001100000111011100000010011 *
b1001011001000000011111010010110 #
b1001011001000000011111010010110 )
b1100 (
1&
#220000
0&
#225000
b0 3
b1 O
10
1-
1"
b0 ]
11
b1 A
b1 H
b1 V
b1 c
b1000 7
b11 9
b11 >
b100 @
b1011 E
b100 G
b0 L
b1101 N
b1000 S
b111 U
b11 Z
b1000 \
b1100 a
b1001 h
b10 j
b1011 6
b110 =
b1101 D
b1101 K
b1111 R
b1001 Y
b101 `
b1011 g
b1111 8
b11 5
b1100 ?
b101 <
b100 F
b110 C
b1011 M
b1101 J
b111 T
b111 Q
b100 [
b1010 X
b1111 b
b1001 _
b11101111010001111011010011001111 !
b11101111010001111011010011001111 +
b1110 i
b10 f
b10110101100111111101110101101011 $
b10110101100111111101110101101011 *
b101001101001111101011001010011 #
b101001101001111101011001010011 )
b1101 (
1&
#230000
0&
#235000
b1 3
b0 O
01
00
0.
02
b0 H
0/
b0 V
b1100 7
b1 S
b110 U
b101 h
b10 9
b1010 >
b0 @
b100 E
b1010 G
b111 L
b0 N
b100 Z
b1 \
b110 a
b0 j
b1110 6
b1010 =
b1110 D
b11 K
b1101 T
b110 R
b101 Y
b111 `
b101 g
b1 8
b10 5
b1010 ?
b0 <
b1000 F
b1010 C
b111 M
b100 J
b110 [
b1 X
b1001 b
b1 _
b1101001011011010111100010100001 !
b1101001011011010111100010100001 +
b110 i
b0 f
b1010111010101100011111010101110 $
b1010111010101100011111010101110 *
b1000101110100101000000010 #
b1000101110100101000000010 )
b1110 (
1&
#240000
0&
#245000
b1 e
12
b0 A
b1 V
0-
b11 L
b100 N
b11 9
b1110 >
b1011 E
b0 G
b100 U
b1000 \
b1111 h
b11 6
b10 =
b1001 D
b100 K
b100 R
b1000 Y
b1 `
b1001 g
b1111 5
b1111 ?
b1100 <
b1011 F
b10 C
b1011 M
b111 J
b1001 T
b101 Q
b100 [
b1100 X
b1000 b
b111 _
b0 i
b110 f
b1000010010011011101111110010 !
b1000010010011011101111110010 +
b10 8
0%
b10010001100001000100100100100011 $
b10010001100001000100100100100011 *
b1100111110001010111001011001111 #
b1100111110001010111001011001111 )
b1111 (
1&
#250000
0&
#255000
1"
b0 e
01
b1 ]
b1 ;
1,
02
b1 A
1.
b0 V
1-
b110 7
b1111 >
b1011 a
b100 c
b111 h
b1000 9
b110 E
b1000 G
b100 L
b0 N
b10 S
b1 U
b11 \
b1100 6
b1111 ?
b11 =
b1100 D
b1 R
b11 Y
b1110 `
b1000 i
b1 g
b110 8
b1010 5
b110 F
b1010 C
b100 M
b0 J
b100 T
b11 Q
b1011 [
b111 X
b10000100101101000100011011110110 !
b10000100101101000100011011110110 +
b100 b
b101 _
b11110001100010100110000111100 $
b11110001100010100110000111100 *
b1100101011100110000101011001010 #
b1100101011100110000101011001010 )
b10000 (
1&
#260000
0&
#265000
b1 H
1/
0,
b0 V
b0 ]
0"
b1 O
b0 3
b0 ;
b0 A
10
0.
0-
b1 d
b1011 7
b0 9
b1100 >
b10 E
b1101 L
b1110 Z
b101 a
b0 c
b110 h
b1 G
b10 N
b1010 S
b100 U
b0 \
b1000 j
b1011 8
b1 6
b100 =
b11 D
b1011 K
b100 R
b1100 Y
b101 b
b0 `
b1010 g
b1100 ?
b1000 <
b100 F
b1 C
b10 M
b110 J
b11 T
b1110 Q
b1110 [
b10 X
b1100101111000110010010011001011 !
b1100101111000110010010011001011 +
b110 i
b1100 f
b10100000110001001011001101000001 $
b10100000110001001011001101000001 *
b11000101001011100110000110001010 #
b11000101001011100110000110001010 )
b10001 (
1&
#270000
0&
#275000
b1 ]
b1 e
b0 O
11
b1 3
b0 d
b1 ;
10
12
b1000 9
b1010 Z
b100 c
b0 j
b1 7
b1111 >
b1 E
b10 G
b1110 L
b1 N
b0 U
b1000 a
b1111 h
b1001 6
b1000 =
b10 D
b1 K
b1010 R
b1010 [
b1000 Y
b100 `
b100 g
b1000 5
b0 ?
b111 <
b110 F
b11 C
b1 M
b1111 J
b1011 T
b0 Q
b0 b
b1100 _
b1111 i
b1011 f
b11110000101010110001011000000010 !
b11110000101010110001011000000010 +
b10 8
1%
b1000100100010100001001010001001 $
b1000100100010100001001010001001 *
b10111100001000001111001101111000 #
b10111100001000001111001101111000 )
b10010 (
1&
#280000
0&
#285000
1"
b0 ;
b0 ]
b0 e
01
1.
b1 d
b0 3
b1 :
b0 I
1/
1,
02
b0 7
b110 9
b111 >
b1000 @
b1100 E
b1 G
b1001 L
b110 N
b1001 S
b10 U
b100 Z
b11 c
b11 h
b1100 j
b110 6
b1100 =
b1001 D
b1111 K
b1011 R
b100 Y
b11 `
b1110 g
b110 5
b111 ?
b1011 <
b1110 F
b101 C
b110 M
b110 J
b1110 T
b10 Q
b101 [
b0 X
b1110 b
b1011 _
b1100 i
b1101 f
b11001110010111100110111001111100 !
b11001110010111100110111001111100 +
b1100 8
0%
b11100011010010111111100111000110 $
b11100011010010111111100111000110 *
b11011011000000100110010110110110 #
b11011011000000100110010110110110 )
b10011 (
1&
#290000
0&
#295000
b10100 (
1&
