02_alu/alu.v

module alu
#(
	parameter	NBIT	= 32
)(
	output	reg	[NBIT-1 : 0]	o_data,
	output	reg					o_cout,
	input		[NBIT-1 : 0]	i_data_a,
	input		[NBIT-1 : 0]	i_data_b,
	input		[3:0]			i_fc,
	input						i_clk,
	input						i_rstn
);

	always @(*) begin
		if(!i_rstn) begin
			o_data	<= 0;
			o_cout	<= 0;
		end else begin
			case(i_fc)
				3'b000 : o_data <= i_data_a & i_data_b;
				3'b001 : o_data <= i_data_a | i_data_b;
				3'b010 : {o_cout, o_data} <= i_data_a + i_data_b;
				3'b011 : o_data <= 0;
				3'b100 : o_data <= i_data_a & ~i_data_b;
				3'b101 : o_data <= i_data_a | ~i_data_b;
				3'b110 : o_data <= i_data_a - ~i_data_b;
				3'b111 : o_data <= (i_data_a < i_data_b) ? 1 : 0;
				default : o_data <= 0;
			endcase
		end
	end
endmodule

02_alu/alu_tb.v
//-------------------------------
//Define & Include
//-------------------------------
`define NBIT		32
`define SIMCYCLE	5
`define CLKFREQ		100
`include "alu.v"

module alu_tb;

//-------------------------------
//Signal Declarations: wire
//-------------------------------
	wire	[`NBIT-1 : 0]	o_data;
	wire					o_cout;

//-------------------------------
//Signal Declarations: reg 
//-------------------------------
	reg		[`NBIT-1 : 0]	i_data_a;
	reg		[`NBIT-1 : 0]	i_data_b;
	reg		[3:0]			i_fc;
	reg						i_clk;
	reg						i_rstn;
	reg		[8*32-1 : 0]	current_function;

//-------------------------------
//CLK Generate
//-------------------------------
always #(500/`CLKFREQ) i_clk = ~i_clk;

//-------------------------------
//Module Instance
//-------------------------------
alu u_alu
(
	.o_data   		(	o_data  	),
	.o_cout    		(	o_cout   	),
	.i_data_a 		(	i_data_a	),
	.i_data_b 		(	i_data_b	),
	.i_fc     		(	i_fc    	),
	.i_clk    		(	i_clk   	),
	.i_rstn   		(	i_rstn  	)
);

//-------------------------------
//Tasks
//-------------------------------
task init;
	begin
		i_data_a	= 0;
		i_data_b	= 0;		
		i_fc		= 0;   		
        i_clk 		= 0;
        i_rstn		= 1;
			
		@(posedge i_clk);
		i_rstn	= 0;

		repeat(20) begin
			@(posedge i_clk);
		end
		
        i_rstn	= 1;

	end
endtask

//-------------------------------
//Test Start
//-------------------------------
integer i;
	initial begin
		init();
		for(i=0;i<`SIMCYCLE;i++) begin
			i_fc = 3'b000;
			i_data_a = $urandom;
			i_data_b = $urandom;
			current_function = " A & B ";
			@(posedge i_clk);
		end
		for(i=0;i<`SIMCYCLE;i++) begin
			i_fc = 3'b001;
			i_data_a = $urandom;
			i_data_b = $urandom;
			current_function = " A | B ";
			@(posedge i_clk);
		end
		for(i=0;i<`SIMCYCLE;i++) begin
			i_fc = 3'b010;
			i_data_a = $urandom;
			i_data_b = $urandom;
			current_function = " A + B ";
			@(posedge i_clk);
		end
		for(i=0;i<`SIMCYCLE;i++) begin
			i_fc = 3'b100;
			i_data_a = $urandom;
			i_data_b = $urandom;
			current_function = " A & ~B ";
			@(posedge i_clk);
		end
		for(i=0;i<`SIMCYCLE;i++) begin
			i_fc = 3'b101;
			i_data_a = $urandom;
			i_data_b = $urandom;
			current_function = " A | ~B ";
			@(posedge i_clk);
		end
		for(i=0;i<`SIMCYCLE;i++) begin
			i_fc = 3'b110;
			i_data_a = $urandom;
			i_data_b = $urandom;
			current_function = " A - ~B ";
			@(posedge i_clk);
		end
		for(i=0;i<`SIMCYCLE;i++) begin
			i_fc = 3'b111;
			i_data_a = $urandom;
			i_data_b = $urandom;
			current_function = " A < B ";
			@(posedge i_clk);
		end
		#100;
		$finish;
	end

//-------------------------------
//Dump VCD
//-------------------------------
reg [8*32-1:0]	vcd_file;
	initial begin
		if ($value$plusargs("vcd_file=%s", vcd_file)) begin
			$dumpfile(vcd_file);
			$dumpvars;
		end else begin
			$dumpfile("alu_tb.vcd");
			$dumpvars;
		end
	end
endmodule

02_alu/vcd/alu.vcd
$date
	Sat Jul  6 18:57:26 2024
$end
$version
	Icarus Verilog
$end
$timescale
	1ps
$end
$scope module alu_tb $end
$var wire 32 ! o_data [31:0] $end
$var wire 1 " o_cout $end
$var reg 256 # current_function [255:0] $end
$var reg 1 $ i_clk $end
$var reg 32 % i_data_a [31:0] $end
$var reg 32 & i_data_b [31:0] $end
$var reg 4 ' i_fc [3:0] $end
$var reg 1 ( i_rstn $end
$var reg 256 ) vcd_file [255:0] $end
$var integer 32 * i [31:0] $end
$scope module u_alu $end
$var wire 1 $ i_clk $end
$var wire 32 + i_data_a [31:0] $end
$var wire 32 , i_data_b [31:0] $end
$var wire 4 - i_fc [3:0] $end
$var wire 1 ( i_rstn $end
$var reg 1 " o_cout $end
$var reg 32 . o_data [31:0] $end
$upscope $end
$scope task init $end
$upscope $end
$upscope $end
$enddefinitions $end
#0
$dumpvars
b0 .
b0 -
b0 ,
b0 +
bx *
b101110001011110111011001100011011001000010111101100001011011000111010100101110011101100110001101100100 )
1(
b0 '
b0 &
b0 %
0$
bx #
x"
b0 !
$end
#5000
0"
0(
1$
#10000
0$
#15000
1$
#20000
0$
#25000
1$
#30000
0$
#35000
1$
#40000
0$
#45000
1$
#50000
0$
#55000
1$
#60000
0$
#65000
1$
#70000
0$
#75000
1$
#80000
0$
#85000
1$
#90000
0$
#95000
1$
#100000
0$
#105000
1$
#110000
0$
#115000
1$
#120000
0$
#125000
1$
#130000
0$
#135000
1$
#140000
0$
#145000
1$
#150000
0$
#155000
1$
#160000
0$
#165000
1$
#170000
0$
#175000
1$
#180000
0$
#185000
1$
#190000
0$
#195000
1$
#200000
0$
#205000
b10001010000000000 !
b10001010000000000 .
b100000010000010010000000100110001000000100001000100000 #
b1000000100010010101111010000001 &
b1000000100010010101111010000001 ,
b10010010000101010011010100100100 %
b10010010000101010011010100100100 +
b0 *
1(
1$
#210000
0$
#215000
b100000000101011000000001 !
b100000000101011000000001 .
b110001111100000101011001100011 &
b110001111100000101011001100011 ,
b100100001001101011000001001 %
b100100001001101011000001001 +
b1 *
1$
#220000
0$
#225000
b10000110100110010001100100001101 !
b10000110100110010001100100001101 .
b11000110110111111001100110001101 &
b11000110110111111001100110001101 ,
b10000110101110010111101100001101 %
b10000110101110010111101100001101 +
b10 *
1$
#230000
0$
#235000
b100000000000000000 !
b100000000000000000 .
b1001001101110101001000010010 &
b1001001101110101001000010010 ,
b110010110000101000010001100101 %
b110010110000101000010001100101 +
b11 *
1$
#240000
0$
#245000
b10000000110100111100000100000001 !
b10000000110100111100000100000001 .
b10000110110101111100110100001101 &
b10000110110101111100110100001101 ,
b10000000111100111110001100000001 %
b10000000111100111110001100000001 +
b100 *
1$
#250000
0$
#255000
b10111111101011111111110101111111 !
b10111111101011111111110101111111 .
b100000010000010010000001111100001000000100001000100000 #
b10011110100011011100110100111101 &
b10011110100011011100110100111101 ,
b10111011001000111111000101110110 %
b10111011001000111111000101110110 +
b1 '
b1 -
b0 *
1$
#260000
0$
#265000
b11110110111111011111011111101101 !
b11110110111111011111011111101101 .
b11000110001011011111011110001100 &
b11000110001011011111011110001100 ,
b11110110110101000101011111101101 %
b11110110110101000101011111101101 +
b1 *
1$
#270000
0$
#275000
b11111111111111111110110111111111 !
b11111111111111111110110111111111 .
b1100011001101110010010011000110 &
b1100011001101110010010011000110 ,
b11111100111111011110100111111001 %
b11111100111111011110100111111001 +
b10 *
1$
#280000
0$
#285000
b1110111111101111101011011101111 !
b1110111111101111101011011101111 .
b1010101000100111101001010101010 &
b1010101000100111101001010101010 ,
b1100010111101111000010011000101 %
b1100010111101111000010011000101 +
b11 *
1$
#290000
0$
#295000
b11111011111111111111011111110111 !
b11111011111111111111011111110111 .
b111011110100100111001001110111 &
b111011110100100111001001110111 ,
b11110010101011111111011111100101 %
b11110010101011111111011111100101 +
b100 *
1$
#300000
0$
#305000
b11010001000111111011000110100001 !
b11010001000111111011000110100001 .
b100000010000010010000000101011001000000100001000100000 #
b11000111111011001101101110001111 &
b11000111111011001101101110001111 ,
b1001001100101101011000010010 %
b1001001100101101011000010010 +
b10 '
b10 -
b0 *
1$
#310000
0$
#315000
1"
b1100000101001110000000011000000 !
b1100000101001110000000011000000 .
b1100111011101101001011011001110 &
b1100111011101101001011011001110 ,
b11111001001100000110100111110010 %
b11111001001100000110100111110010 +
b1 *
1$
#320000
0$
#325000
0"
b11010110110010101100100110101101 !
b11010110110010101100100110101101 .
b1100010110010100100111011000101 &
b1100010110010100100111011000101 ,
b1110100000000000111101011101000 %
b1110100000000000111101011101000 +
b10 *
1$
#330000
0$
#335000
1"
b1100111001100111001000011001 !
b1100111001100111001000011001 .
b1011110100011100010100010111101 &
b1011110100011100010100010111101 ,
b10101110010110000100100101011100 %
b10101110010110000100100101011100 +
b11 *
1$
#340000
0$
#345000
0"
b1001001010100100111111010010010 !
b1001001010100100111111010010010 .
b110010101001110010011001100101 &
b110010101001110010011001100101 ,
b10110101010110101100000101101 %
b10110101010110101100000101101 +
b100 *
1$
#350000
0$
#355000
b110000100011000110000001100001 !
b110000100011000110000001100001 .
b10000001000001001000000010011000100000011111100100001000100000 #
b10000101011100111000011100001010 &
b10000101011100111000011100001010 ,
b110001111011110110001001100011 %
b110001111011110110001001100011 +
b100 '
b100 -
b0 *
1$
#360000
0$
#365000
b1000000000110110000001010000000 !
b1000000000110110000001010000000 .
b10010000011001000010000100100000 &
b10010000011001000010000100100000 ,
b1000000001110110010001010000000 %
b1000000001110110010001010000000 +
b1 *
1$
#370000
0$
#375000
b10010001001100000000000100100010 !
b10010001001100000000000100100010 .
b1001110110011001100110010011101 &
b1001110110011001100110010011101 ,
b11010101011110000100010110101010 %
b11010101011110000100010110101010 +
b10 *
1$
#380000
0$
#385000
b1000010001000000000011010000100 !
b1000010001000000000011010000100 .
b1001100000111011100000010011 &
b1001100000111011100000010011 ,
b1001011001000000011111010010110 %
b1001011001000000011111010010110 +
b11 *
1$
#390000
0$
#395000
b110000110000010100000001100 !
b110000110000010100000001100 .
b101001101001111101011001010011 &
b101001101001111101011001010011 ,
b110101111000011100000001101 %
b110101111000011100000001101 +
b100 *
1$
#400000
0$
#405000
b10110101110111111101110101101011 !
b10110101110111111101110101101011 .
b10000001000001001000000111110000100000011111100100001000100000 #
b1101010101001100010101011010101 &
b1101010101001100010101011010101 ,
b10110101100111111101110101101011 %
b10110101100111111101110101101011 +
b101 '
b101 -
b0 *
1$
#410000
0$
#415000
b10101001101111111100101101010011 !
b10101001101111111100101101010011 .
b1010111010101100011111010101110 &
b1010111010101100011111010101110 ,
b1000101110100101000000010 %
b1000101110100101000000010 +
b1 *
1$
#420000
0$
#425000
b10011110111111111110110100111101 !
b10011110111111111110110100111101 .
b1100111110001010111001011001111 &
b1100111110001010111001011001111 ,
b10001110111111111110100100011101 %
b10001110111111111110100100011101 +
b10 *
1$
#430000
0$
#435000
b11111011111101101101101111110111 !
b11111011111101101101101111110111 .
b10000101000010010110010100001010 &
b10000101000010010110010100001010 ,
b10010001100001000100100100100011 %
b10010001100001000100100100100011 +
b11 *
1$
#440000
0$
#445000
b11100101111111111011101111001011 !
b11100101111111111011101111001011 .
b11110001100010100110000111100 &
b11110001100010100110000111100 ,
b1100101011100110000101011001010 %
b1100101011100110000101011001010 +
b100 *
1$
#450000
0$
#455000
b10111110100101110001111101111101 !
b10111110100101110001111101111101 .
b10000001000001001000000010110100100000011111100100001000100000 #
b11000101001011100110000110001010 &
b11000101001011100110000110001010 ,
b11111001011010001011110111110010 %
b11111001011010001011110111110010 +
b110 '
b110 -
b0 *
1$
#460000
0$
#465000
b1101000011111110100000011010 !
b1101000011111110100000011010 .
b1101100010010110011010011011000 &
b1101100010010110011010011011000 ,
b10100000110001001011001101000001 %
b10100000110001001011001101000001 +
b1 *
1$
#470000
0$
#475000
b101010110000011000000010 !
b101010110000011000000010 .
b1000100100010100001001010001001 &
b1000100100010100001001010001001 ,
b10111100001000001111001101111000 %
b10111100001000001111001101111000 +
b10 *
1$
#480000
0$
#485000
b11010000110001110111001110100010 !
b11010000110001110111001110100010 .
b11011011000000100110010110110110 &
b11011011000000100110010110110110 ,
b11110101110001010000110111101011 %
b11110101110001010000110111101011 +
b11 *
1$
#490000
0$
#495000
b10111010011000010000110101110101 !
b10111010011000010000110101110101 .
b11010111000101010001001110101110 &
b11010111000101010001001110101110 ,
b11100011010010111111100111000110 %
b11100011010010111111100111000110 +
b100 *
1$
#500000
0$
#505000
b1 !
b1 .
b100000010000010010000000111100001000000100001000100000 #
b10010101000011111101110100101010 &
b10010101000011111101110100101010 ,
b1011110011101010000001010111100 %
b1011110011101010000001010111100 +
b111 '
b111 -
b0 *
1$
#510000
0$
#515000
b111000100101111011111001110001 &
b111000100101111011111001110001 ,
b101110101111001101000001011 %
b101110101111001101000001011 +
b1 *
1$
#520000
0$
#525000
b0 !
b0 .
b10100111111100100101010101001111 &
b10100111111100100101010101001111 ,
b11000010111100100100000110000101 %
b11000010111100100100000110000101 +
b10 *
1$
#530000
0$
#535000
b1 !
b1 .
b10011101000001100011001100111010 &
b10011101000001100011001100111010 ,
b11101110011000110000000111011 %
b11101110011000110000000111011 +
b11 *
1$
#540000
0$
#545000
b10001010101010100100101100010101 &
b10001010101010100100101100010101 ,
b111111001000110011001001111110 %
b111111001000110011001001111110 +
b100 *
1$
#550000
0$
#555000
b101 *
1$
